pyeqx/common/__init__.py
pyeqx/common/helper.py
pyeqx/common/result.py
pyeqx/common/utils.py
pyeqx_common-0.1.1.dist-info/METADATA
pyeqx_common-0.1.1.dist-info/WHEEL
pyeqx_common-0.1.1.dist-info/top_level.txt
pyeqx_common-0.1.1.dist-info/RECORD
