Metadata-Version: 2.4
Name: pyeqx-common
Version: 0.1.1
Summary: Python library for common method use in PyEQX ecosystem.
Author: ESBM Cronus
Classifier: Programming Language :: Python :: 3
Requires-Python: >=3.11
Provides-Extra: dev
Requires-Dist: black; extra == "dev"
Requires-Dist: ruff; extra == "dev"
Requires-Dist: build; extra == "dev"
Requires-Dist: twine; extra == "dev"
Requires-Dist: python-dotenv; extra == "dev"
Requires-Dist: pytest; extra == "dev"
Requires-Dist: pytest-cov; extra == "dev"
Requires-Dist: pytest-mock; extra == "dev"
Requires-Dist: pytest-watch; extra == "dev"
